MANIFEST.in
README.md
requirements.txt
setup.py
flexer/__init__.py
flexer/cli.py
flexer/commands.py
flexer/config.py
flexer/context.py
flexer/module_template.py
flexer/runner.py
flexer/utils.py
flexer.egg-info/PKG-INFO
flexer.egg-info/SOURCES.txt
flexer.egg-info/dependency_links.txt
flexer.egg-info/entry_points.txt
flexer.egg-info/requires.txt
flexer.egg-info/top_level.txt
flexer/clients/__init__.py
flexer/clients/cmp.py
flexer/clients/nflex.py
flexer/connector_tests/__init__.py
flexer/connector_tests/test_base.py
flexer/templates/metric_connector/main.py.j2
flexer/templates/metric_connector/test-data.json.j2
flexer/templates/resource_connector/main.py.j2
flexer/templates/test/main.py.j2