Metadata-Version: 1.1
Name: flexer
Version: 1.7.2
Summary: Flexer is a command line tool for interacting with nFlex and running nFlex modules locally.
Home-page: http://www.ntt.com
Author: NTT communications
Author-email: minder@nexus.ntteo.net
License: GNU General Public License v2 (GPLv2)
Platform: UNKNOWN
Classifier: Development Status :: 4 - Beta
Classifier: Environment :: Console
Classifier: Intended Audience :: Developers
Classifier: License :: OSI Approved :: GNU General Public License v2 (GPLv2)
Classifier: Natural Language :: English
Classifier: Programming Language :: Python :: 2.7
Classifier: Programming Language :: Python :: 3.3
Classifier: Programming Language :: Python :: 3.4
Classifier: Programming Language :: Python :: 3.5
Classifier: Programming Language :: Python :: 3.6
Classifier: Topic :: Software Development
